{
    "@class": "com.kony.gen.viz.model.component.KVizButton",
    "DNDConfig": null,
    "_height_": {
        "type": "string",
        "value": "50dp"
    },
    "_left_": {
        "type": "string",
        "value": "14dp"
    },
    "_margin_": [
        6,
        6,
        6,
        6
    ],
    "_padding_": [
        0,
        0,
        0,
        0
    ],
    "_skin_": "s7e63760a5d34d828e8d8723616affcd",
    "_text_": "Button",
    "_top_": {
        "type": "string",
        "value": "34dp"
    },
    "_width_": {
        "type": "string",
        "value": "300dp"
    },
    "canUpdateUI": true,
    "containerweight": 100,
    "contentalignment": 5,
    "displaytext": true,
    "focusskin": "s704af52c5534ec692f24076a0a174b1",
    "id": "Button0c3e3adc7aa4f43",
    "info": null,
    "iscustomlayout": false,
    "isvisible": true,
    "kuid": "c21f5dec9d294a18961386b587e62adf",
    "name": "kony.ui.Button",
    "parent": "Form1",
    "pf": "Form1",
    "retaincontentalignment": false,
    "retainflexpositionproperties": false,
    "wType": "Button",
    "zindex": 1
}